{
	"format_version": "1.12.0",
	"minecraft:geometry": [
		{
			"description": {
				"identifier": "geometry.stick",
				"texture_width": 64,
				"texture_height": 64,
				"visible_bounds_width": 4,
				"visible_bounds_height": 4.5,
				"visible_bounds_offset": [0, 1.75, 0]
			},
			"bones": [
				{
					"name": "balloons",
					"pivot": [1, 7, 0]
				},
				{
					"name": "first",
					"parent": "balloons",
					"pivot": [-6, 13, -3],
					"rotation": [32.5, -27.5, 0]
				},
				{
					"name": "bone15",
					"parent": "first",
					"pivot": [0.78381, 21.01199, -1.58851],
					"rotation": [-20, 7.5, -12.5]
				},
				{
					"name": "bone16",
					"parent": "bone15",
					"pivot": [-0.21619, 40.01199, -1.58851],
					"cubes": [
						{
							"origin": [-4.21619, 40.01199, -5.58851],
							"size": [9, 10, 9],
							"uv": {
								"north": {"uv": [7, 53], "uv_size": [9, 10]},
								"east": {"uv": [7, 53], "uv_size": [9, 10]},
								"south": {"uv": [7, 53], "uv_size": [9, 10]},
								"west": {"uv": [7, 53], "uv_size": [9, 10]},
								"up": {"uv": [16, 63], "uv_size": [-9, -10]},
								"down": {"uv": [16, 63], "uv_size": [-9, -10]}
							}
						},
						{
							"origin": [-3.21619, 39.01199, -4.58851],
							"size": [7, 12, 7],
							"uv": {
								"north": {"uv": [7, 63], "uv_size": [7, 1]},
								"east": {"uv": [0, 56], "uv_size": [7, 8]},
								"south": {"uv": [7, 63], "uv_size": [7, 1]},
								"west": {"uv": [7, 63], "uv_size": [7, 1]},
								"up": {"uv": [7, 64], "uv_size": [-7, -8]},
								"down": {"uv": [16, 63], "uv_size": [-9, -10]}
							}
						},
						{
							"origin": [-3.21619, 41.01199, -6.58851],
							"size": [7, 8, 11],
							"uv": {
								"north": {"uv": [0, 56], "uv_size": [7, 8]},
								"east": {"uv": [2, 48], "uv_size": [1, 8]},
								"south": {"uv": [0, 56], "uv_size": [7, 8]},
								"west": {"uv": [0, 56], "uv_size": [7, 8]},
								"up": {"uv": [7, 64], "uv_size": [-7, -8]},
								"down": {"uv": [7, 64], "uv_size": [-7, -8]}
							}
						},
						{
							"origin": [-5.21619, 41.01199, -4.58851],
							"size": [11, 8, 7],
							"uv": {
								"north": {"uv": [0, 56], "uv_size": [7, 8]},
								"east": {"uv": [0, 56], "uv_size": [7, 8]},
								"south": {"uv": [0, 56], "uv_size": [7, 8]},
								"west": {"uv": [0, 56], "uv_size": [7, 8]},
								"up": {"uv": [2, 56], "uv_size": [-1, -8]},
								"down": {"uv": [1, 56], "uv_size": [-1, -8]}
							}
						}
					]
				},
				{
					"name": "bone17",
					"parent": "bone15",
					"pivot": [0.78381, 21.01199, -1.58851],
					"cubes": [
						{
							"origin": [0.18381, 6.01199, -1.58851],
							"size": [0.2, 34, 0.5],
							"uv": {
								"north": {"uv": [16, 45], "uv_size": [1, 19]},
								"east": {"uv": [16, 45], "uv_size": [1, 19]},
								"south": {"uv": [16, 45], "uv_size": [1, 19]},
								"west": {"uv": [16, 45], "uv_size": [1, 19]},
								"up": {"uv": [17, 64], "uv_size": [-1, -19]},
								"down": {"uv": [17, 64], "uv_size": [-1, -19]}
							}
						}
					]
				},
				{
					"name": "bone18",
					"parent": "first",
					"pivot": [-1.83094, 13.9917, 0.82008],
					"rotation": [-40, -12.5, -5]
				},
				{
					"name": "bone19",
					"parent": "bone18",
					"pivot": [-2.83094, 32.9917, 0.82008],
					"cubes": [
						{
							"origin": [-6.83094, 32.9917, -3.17992],
							"size": [9, 10, 9],
							"uv": {
								"north": {"uv": [7, 53], "uv_size": [9, 10]},
								"east": {"uv": [7, 53], "uv_size": [9, 10]},
								"south": {"uv": [7, 53], "uv_size": [9, 10]},
								"west": {"uv": [7, 53], "uv_size": [9, 10]},
								"up": {"uv": [16, 63], "uv_size": [-9, -10]},
								"down": {"uv": [16, 63], "uv_size": [-9, -10]}
							}
						},
						{
							"origin": [-5.83094, 31.9917, -2.17992],
							"size": [7, 12, 7],
							"uv": {
								"north": {"uv": [7, 63], "uv_size": [7, 1]},
								"east": {"uv": [0, 56], "uv_size": [7, 8]},
								"south": {"uv": [7, 63], "uv_size": [7, 1]},
								"west": {"uv": [7, 63], "uv_size": [7, 1]},
								"up": {"uv": [7, 64], "uv_size": [-7, -8]},
								"down": {"uv": [16, 63], "uv_size": [-9, -10]}
							}
						},
						{
							"origin": [-5.83094, 33.9917, -4.17992],
							"size": [7, 8, 11],
							"uv": {
								"north": {"uv": [0, 56], "uv_size": [7, 8]},
								"east": {"uv": [2, 48], "uv_size": [1, 8]},
								"south": {"uv": [0, 56], "uv_size": [7, 8]},
								"west": {"uv": [0, 56], "uv_size": [7, 8]},
								"up": {"uv": [7, 64], "uv_size": [-7, -8]},
								"down": {"uv": [7, 64], "uv_size": [-7, -8]}
							}
						},
						{
							"origin": [-7.83094, 33.9917, -2.17992],
							"size": [11, 8, 7],
							"uv": {
								"north": {"uv": [0, 56], "uv_size": [7, 8]},
								"east": {"uv": [0, 56], "uv_size": [7, 8]},
								"south": {"uv": [0, 56], "uv_size": [7, 8]},
								"west": {"uv": [0, 56], "uv_size": [7, 8]},
								"up": {"uv": [2, 56], "uv_size": [-1, -8]},
								"down": {"uv": [1, 56], "uv_size": [-1, -8]}
							}
						}
					]
				},
				{
					"name": "bone20",
					"parent": "bone18",
					"pivot": [-1.83094, 13.9917, 0.82008],
					"cubes": [
						{
							"origin": [-2.43094, 1.9917, 0.82008],
							"size": [0.2, 31, 0.5],
							"uv": {
								"north": {"uv": [16, 45], "uv_size": [1, 19]},
								"east": {"uv": [16, 45], "uv_size": [1, 19]},
								"south": {"uv": [16, 45], "uv_size": [1, 19]},
								"west": {"uv": [16, 45], "uv_size": [1, 19]},
								"up": {"uv": [17, 64], "uv_size": [-1, -19]},
								"down": {"uv": [17, 64], "uv_size": [-1, -19]}
							}
						}
					]
				},
				{
					"name": "bone21",
					"parent": "first",
					"pivot": [-0.64498, 14.12409, -5.70572],
					"rotation": [-25, -10, -20]
				},
				{
					"name": "bone22",
					"parent": "bone21",
					"pivot": [-1.64498, 33.12409, -5.70572],
					"cubes": [
						{
							"origin": [-5.64498, 33.12409, -9.70572],
							"size": [9, 10, 9],
							"uv": {
								"north": {"uv": [41, 53], "uv_size": [9, 10]},
								"east": {"uv": [41, 53], "uv_size": [9, 10]},
								"south": {"uv": [41, 53], "uv_size": [9, 10]},
								"west": {"uv": [41, 53], "uv_size": [9, 10]},
								"up": {"uv": [50, 63], "uv_size": [-9, -10]},
								"down": {"uv": [50, 63], "uv_size": [-9, -10]}
							}
						},
						{
							"origin": [-4.64498, 32.12409, -8.70572],
							"size": [7, 12, 7],
							"uv": {
								"north": {"uv": [34, 56], "uv_size": [7, 8]},
								"east": {"uv": [34, 56], "uv_size": [7, 8]},
								"south": {"uv": [34, 56], "uv_size": [7, 8]},
								"west": {"uv": [34, 56], "uv_size": [7, 8]},
								"up": {"uv": [41, 64], "uv_size": [-7, -8]},
								"down": {"uv": [41, 64], "uv_size": [-7, -8]}
							}
						},
						{
							"origin": [-4.64498, 34.12409, -10.70572],
							"size": [7, 8, 11],
							"uv": {
								"north": {"uv": [34, 56], "uv_size": [7, 8]},
								"east": {"uv": [34, 56], "uv_size": [7, 8]},
								"south": {"uv": [34, 56], "uv_size": [7, 8]},
								"west": {"uv": [34, 56], "uv_size": [7, 8]},
								"up": {"uv": [41, 64], "uv_size": [-7, -8]},
								"down": {"uv": [41, 64], "uv_size": [-7, -8]}
							}
						},
						{
							"origin": [-6.64498, 34.12409, -8.70572],
							"size": [11, 8, 7],
							"uv": {
								"north": {"uv": [34, 56], "uv_size": [7, 8]},
								"east": {"uv": [34, 56], "uv_size": [7, 8]},
								"south": {"uv": [34, 56], "uv_size": [7, 8]},
								"west": {"uv": [34, 56], "uv_size": [7, 8]},
								"up": {"uv": [41, 64], "uv_size": [-7, -8]},
								"down": {"uv": [41, 64], "uv_size": [-7, -8]}
							}
						}
					]
				},
				{
					"name": "bone23",
					"parent": "bone21",
					"pivot": [-0.64498, 14.12409, -5.70572],
					"cubes": [
						{
							"origin": [-1.24498, 7.12409, -5.70572],
							"size": [0.2, 26, 0.5],
							"uv": {
								"north": {"uv": [16, 45], "uv_size": [1, 19]},
								"east": {"uv": [16, 45], "uv_size": [1, 19]},
								"south": {"uv": [16, 45], "uv_size": [1, 19]},
								"west": {"uv": [16, 45], "uv_size": [1, 19]},
								"up": {"uv": [17, 64], "uv_size": [-1, -19]},
								"down": {"uv": [17, 64], "uv_size": [-1, -19]}
							}
						}
					]
				},
				{
					"name": "bone24",
					"parent": "first",
					"pivot": [1.66103, 23.43107, -3.09371],
					"rotation": [-7.5, -7.5, 10]
				},
				{
					"name": "bone25",
					"parent": "bone24",
					"pivot": [0.66103, 42.43107, -3.09371],
					"cubes": [
						{
							"origin": [-3.33897, 42.43107, -7.09371],
							"size": [9, 10, 9],
							"uv": {
								"north": {"uv": [34, 56], "uv_size": [7, 8]},
								"east": {"uv": [34, 56], "uv_size": [7, 8]},
								"south": {"uv": [34, 56], "uv_size": [7, 8]},
								"west": {"uv": [34, 56], "uv_size": [7, 8]},
								"up": {"uv": [41, 64], "uv_size": [-7, -8]},
								"down": {"uv": [41, 64], "uv_size": [-7, -8]}
							}
						},
						{
							"origin": [-2.33897, 41.43107, -6.09371],
							"size": [7, 12, 7],
							"uv": {
								"north": {"uv": [34, 56], "uv_size": [7, 8]},
								"east": {"uv": [34, 56], "uv_size": [7, 8]},
								"south": {"uv": [34, 56], "uv_size": [7, 8]},
								"west": {"uv": [34, 56], "uv_size": [7, 8]},
								"up": {"uv": [41, 64], "uv_size": [-7, -8]},
								"down": {"uv": [41, 64], "uv_size": [-7, -8]}
							}
						},
						{
							"origin": [-2.33897, 43.43107, -8.09371],
							"size": [7, 8, 11],
							"uv": {
								"north": {"uv": [34, 56], "uv_size": [7, 8]},
								"east": {"uv": [34, 56], "uv_size": [7, 8]},
								"south": {"uv": [34, 56], "uv_size": [7, 8]},
								"west": {"uv": [34, 56], "uv_size": [7, 8]},
								"up": {"uv": [41, 64], "uv_size": [-7, -8]},
								"down": {"uv": [41, 64], "uv_size": [-7, -8]}
							}
						},
						{
							"origin": [-4.33897, 43.43107, -6.09371],
							"size": [11, 8, 7],
							"uv": {
								"north": {"uv": [34, 56], "uv_size": [7, 8]},
								"east": {"uv": [34, 56], "uv_size": [7, 8]},
								"south": {"uv": [34, 56], "uv_size": [7, 8]},
								"west": {"uv": [34, 56], "uv_size": [7, 8]},
								"up": {"uv": [41, 64], "uv_size": [-7, -8]},
								"down": {"uv": [41, 64], "uv_size": [-7, -8]}
							}
						}
					]
				},
				{
					"name": "bone26",
					"parent": "bone24",
					"pivot": [1.66103, 23.43107, -3.09371],
					"cubes": [
						{
							"origin": [1.06103, 6.43107, -3.09371],
							"size": [0.2, 36, 0.5],
							"uv": {
								"north": {"uv": [16, 45], "uv_size": [1, 19]},
								"east": {"uv": [16, 45], "uv_size": [1, 19]},
								"south": {"uv": [16, 45], "uv_size": [1, 19]},
								"west": {"uv": [16, 45], "uv_size": [1, 19]},
								"up": {"uv": [17, 64], "uv_size": [-1, -19]},
								"down": {"uv": [17, 64], "uv_size": [-1, -19]}
							}
						}
					]
				},
				{
					"name": "second",
					"parent": "balloons",
					"pivot": [1, 7, 0]
				},
				{
					"name": "bone10",
					"parent": "second",
					"pivot": [2, 14, 3],
					"rotation": [-22.5, 15, 7.5]
				},
				{
					"name": "bone11",
					"parent": "bone10",
					"pivot": [1, 33, 3],
					"cubes": [
						{
							"origin": [-3, 33, -1],
							"size": [9, 10, 9],
							"uv": {
								"north": {"uv": [24, 53], "uv_size": [9, 10]},
								"east": {"uv": [24, 53], "uv_size": [9, 10]},
								"south": {"uv": [24, 53], "uv_size": [9, 10]},
								"west": {"uv": [24, 53], "uv_size": [9, 10]},
								"up": {"uv": [33, 63], "uv_size": [-9, -10]},
								"down": {"uv": [33, 63], "uv_size": [-9, -10]}
							}
						},
						{
							"origin": [-2, 32, 0],
							"size": [7, 12, 7],
							"uv": {
								"north": {"uv": [17, 56], "uv_size": [7, 8]},
								"east": {"uv": [17, 56], "uv_size": [7, 8]},
								"south": {"uv": [17, 56], "uv_size": [7, 8]},
								"west": {"uv": [17, 56], "uv_size": [7, 8]},
								"up": {"uv": [24, 64], "uv_size": [-7, -8]},
								"down": {"uv": [24, 64], "uv_size": [-7, -8]}
							}
						},
						{
							"origin": [-2, 34, -2],
							"size": [7, 8, 11],
							"uv": {
								"north": {"uv": [17, 56], "uv_size": [7, 8]},
								"east": {"uv": [17, 56], "uv_size": [7, 8]},
								"south": {"uv": [17, 56], "uv_size": [7, 8]},
								"west": {"uv": [17, 56], "uv_size": [7, 8]},
								"up": {"uv": [24, 64], "uv_size": [-7, -8]},
								"down": {"uv": [24, 64], "uv_size": [-7, -8]}
							}
						},
						{
							"origin": [-4, 34, 0],
							"size": [11, 8, 7],
							"uv": {
								"north": {"uv": [17, 56], "uv_size": [7, 8]},
								"east": {"uv": [17, 56], "uv_size": [7, 8]},
								"south": {"uv": [17, 56], "uv_size": [7, 8]},
								"west": {"uv": [17, 56], "uv_size": [7, 8]},
								"up": {"uv": [24, 64], "uv_size": [-7, -8]},
								"down": {"uv": [24, 64], "uv_size": [-7, -8]}
							}
						}
					]
				},
				{
					"name": "bone12",
					"parent": "bone10",
					"pivot": [2, 14, 3],
					"cubes": [
						{
							"origin": [1.4, 7, 3],
							"size": [0.2, 26, 0.5],
							"uv": {
								"north": {"uv": [16, 45], "uv_size": [1, 19]},
								"east": {"uv": [16, 45], "uv_size": [1, 19]},
								"south": {"uv": [16, 45], "uv_size": [1, 19]},
								"west": {"uv": [16, 45], "uv_size": [1, 19]},
								"up": {"uv": [17, 64], "uv_size": [-1, -19]},
								"down": {"uv": [17, 64], "uv_size": [-1, -19]}
							}
						}
					]
				},
				{
					"name": "bone7",
					"parent": "second",
					"pivot": [-2, 16, 4],
					"rotation": [-25, -7.5, -2.5]
				},
				{
					"name": "bone8",
					"parent": "bone7",
					"pivot": [-3, 35, 4],
					"cubes": [
						{
							"origin": [-7, 35, 0],
							"size": [9, 10, 9],
							"uv": {
								"north": {"uv": [41, 53], "uv_size": [9, 10]},
								"east": {"uv": [41, 53], "uv_size": [9, 10]},
								"south": {"uv": [41, 53], "uv_size": [9, 10]},
								"west": {"uv": [41, 53], "uv_size": [9, 10]},
								"up": {"uv": [50, 63], "uv_size": [-9, -10]},
								"down": {"uv": [50, 63], "uv_size": [-9, -10]}
							}
						},
						{
							"origin": [-6, 34, 1],
							"size": [7, 12, 7],
							"uv": {
								"north": {"uv": [34, 56], "uv_size": [7, 8]},
								"east": {"uv": [34, 56], "uv_size": [7, 8]},
								"south": {"uv": [34, 56], "uv_size": [7, 8]},
								"west": {"uv": [34, 56], "uv_size": [7, 8]},
								"up": {"uv": [41, 64], "uv_size": [-7, -8]},
								"down": {"uv": [41, 64], "uv_size": [-7, -8]}
							}
						},
						{
							"origin": [-6, 36, -1],
							"size": [7, 8, 11],
							"uv": {
								"north": {"uv": [34, 56], "uv_size": [7, 8]},
								"east": {"uv": [34, 56], "uv_size": [7, 8]},
								"south": {"uv": [34, 56], "uv_size": [7, 8]},
								"west": {"uv": [34, 56], "uv_size": [7, 8]},
								"up": {"uv": [41, 64], "uv_size": [-7, -8]},
								"down": {"uv": [41, 64], "uv_size": [-7, -8]}
							}
						},
						{
							"origin": [-8, 36, 1],
							"size": [11, 8, 7],
							"uv": {
								"north": {"uv": [34, 56], "uv_size": [7, 8]},
								"east": {"uv": [34, 56], "uv_size": [7, 8]},
								"south": {"uv": [34, 56], "uv_size": [7, 8]},
								"west": {"uv": [34, 56], "uv_size": [7, 8]},
								"up": {"uv": [41, 64], "uv_size": [-7, -8]},
								"down": {"uv": [41, 64], "uv_size": [-7, -8]}
							}
						}
					]
				},
				{
					"name": "bone9",
					"parent": "bone7",
					"pivot": [-2, 16, 4],
					"cubes": [
						{
							"origin": [-2.6, 4, 4],
							"size": [0.2, 31, 0.5],
							"uv": {
								"north": {"uv": [16, 45], "uv_size": [1, 19]},
								"east": {"uv": [16, 45], "uv_size": [1, 19]},
								"south": {"uv": [16, 45], "uv_size": [1, 19]},
								"west": {"uv": [16, 45], "uv_size": [1, 19]},
								"up": {"uv": [17, 64], "uv_size": [-1, -19]},
								"down": {"uv": [17, 64], "uv_size": [-1, -19]}
							}
						}
					]
				},
				{
					"name": "bone4",
					"parent": "second",
					"pivot": [0, 23, 0],
					"rotation": [-2.5, 20, 0]
				},
				{
					"name": "bone5",
					"parent": "bone4",
					"pivot": [-1, 42, 0],
					"cubes": [
						{
							"origin": [-5, 42, -4],
							"size": [9, 10, 9],
							"uv": {
								"north": {"uv": [24, 53], "uv_size": [9, 10]},
								"east": {"uv": [24, 53], "uv_size": [9, 10]},
								"south": {"uv": [24, 53], "uv_size": [9, 10]},
								"west": {"uv": [24, 53], "uv_size": [9, 10]},
								"up": {"uv": [33, 63], "uv_size": [-9, -10]},
								"down": {"uv": [33, 63], "uv_size": [-9, -10]}
							}
						},
						{
							"origin": [-4, 41, -3],
							"size": [7, 12, 7],
							"uv": {
								"north": {"uv": [17, 56], "uv_size": [7, 8]},
								"east": {"uv": [17, 56], "uv_size": [7, 8]},
								"south": {"uv": [17, 56], "uv_size": [7, 8]},
								"west": {"uv": [17, 56], "uv_size": [7, 8]},
								"up": {"uv": [24, 64], "uv_size": [-7, -8]},
								"down": {"uv": [24, 64], "uv_size": [-7, -8]}
							}
						},
						{
							"origin": [-4, 43, -5],
							"size": [7, 8, 11],
							"uv": {
								"north": {"uv": [17, 56], "uv_size": [7, 8]},
								"east": {"uv": [17, 56], "uv_size": [7, 8]},
								"south": {"uv": [17, 56], "uv_size": [7, 8]},
								"west": {"uv": [17, 56], "uv_size": [7, 8]},
								"up": {"uv": [24, 64], "uv_size": [-7, -8]},
								"down": {"uv": [24, 64], "uv_size": [-7, -8]}
							}
						},
						{
							"origin": [-6, 43, -3],
							"size": [11, 8, 7],
							"uv": {
								"north": {"uv": [17, 56], "uv_size": [7, 8]},
								"east": {"uv": [17, 56], "uv_size": [7, 8]},
								"south": {"uv": [17, 56], "uv_size": [7, 8]},
								"west": {"uv": [17, 56], "uv_size": [7, 8]},
								"up": {"uv": [24, 64], "uv_size": [-7, -8]},
								"down": {"uv": [24, 64], "uv_size": [-7, -8]}
							}
						}
					]
				},
				{
					"name": "bone6",
					"parent": "bone4",
					"pivot": [0, 23, 0],
					"cubes": [
						{
							"origin": [-0.6, 9, 0],
							"size": [0.2, 33, 0.5],
							"uv": {
								"north": {"uv": [16, 45], "uv_size": [1, 19]},
								"east": {"uv": [16, 45], "uv_size": [1, 19]},
								"south": {"uv": [16, 45], "uv_size": [1, 19]},
								"west": {"uv": [16, 45], "uv_size": [1, 19]},
								"up": {"uv": [17, 64], "uv_size": [-1, -19]},
								"down": {"uv": [17, 64], "uv_size": [-1, -19]}
							}
						}
					]
				},
				{
					"name": "bone3",
					"parent": "second",
					"pivot": [3, 15, 0],
					"rotation": [-7.5, -7.5, 15]
				},
				{
					"name": "bone2",
					"parent": "bone3",
					"pivot": [2, 34, 0],
					"cubes": [
						{
							"origin": [-2, 34, -4],
							"size": [9, 10, 9],
							"uv": {
								"north": {"uv": [7, 53], "uv_size": [9, 10]},
								"east": {"uv": [7, 53], "uv_size": [9, 10]},
								"south": {"uv": [7, 53], "uv_size": [9, 10]},
								"west": {"uv": [7, 53], "uv_size": [9, 10]},
								"up": {"uv": [16, 63], "uv_size": [-9, -10]},
								"down": {"uv": [16, 63], "uv_size": [-9, -10]}
							}
						},
						{
							"origin": [-1, 33, -3],
							"size": [7, 12, 7],
							"uv": {
								"north": {"uv": [7, 63], "uv_size": [7, 1]},
								"east": {"uv": [0, 56], "uv_size": [7, 8]},
								"south": {"uv": [7, 63], "uv_size": [7, 1]},
								"west": {"uv": [7, 63], "uv_size": [7, 1]},
								"up": {"uv": [7, 64], "uv_size": [-7, -8]},
								"down": {"uv": [16, 63], "uv_size": [-9, -10]}
							}
						},
						{
							"origin": [-1, 35, -5],
							"size": [7, 8, 11],
							"uv": {
								"north": {"uv": [0, 56], "uv_size": [7, 8]},
								"east": {"uv": [2, 48], "uv_size": [1, 8]},
								"south": {"uv": [0, 56], "uv_size": [7, 8]},
								"west": {"uv": [0, 56], "uv_size": [7, 8]},
								"up": {"uv": [7, 64], "uv_size": [-7, -8]},
								"down": {"uv": [7, 64], "uv_size": [-7, -8]}
							}
						},
						{
							"origin": [-3, 35, -3],
							"size": [11, 8, 7],
							"uv": {
								"north": {"uv": [0, 56], "uv_size": [7, 8]},
								"east": {"uv": [0, 56], "uv_size": [7, 8]},
								"south": {"uv": [0, 56], "uv_size": [7, 8]},
								"west": {"uv": [0, 56], "uv_size": [7, 8]},
								"up": {"uv": [2, 56], "uv_size": [-1, -8]},
								"down": {"uv": [1, 56], "uv_size": [-1, -8]}
							}
						}
					]
				},
				{
					"name": "bone",
					"parent": "bone3",
					"pivot": [3, 15, 0],
					"cubes": [
						{
							"origin": [2.4, 6, 0],
							"size": [0.2, 28, 0.5],
							"uv": {
								"north": {"uv": [16, 45], "uv_size": [1, 19]},
								"east": {"uv": [16, 45], "uv_size": [1, 19]},
								"south": {"uv": [16, 45], "uv_size": [1, 19]},
								"west": {"uv": [16, 45], "uv_size": [1, 19]},
								"up": {"uv": [17, 64], "uv_size": [-1, -19]},
								"down": {"uv": [17, 64], "uv_size": [-1, -19]}
							}
						}
					]
				},
				{
					"name": "stick",
					"pivot": [0, 0, 0],
					"cubes": [
						{
							"origin": [-3.05, 1, -3.05],
							"size": [6.1, 1, 6.1],
							"uv": {
								"north": {"uv": [13, 51], "uv_size": [3, 1]},
								"east": {"uv": [13, 48], "uv_size": [3, 1]},
								"south": {"uv": [13, 46], "uv_size": [3, 2]},
								"west": {"uv": [13, 46], "uv_size": [3, 2]},
								"up": {"uv": [16, 48], "uv_size": [-3, -2]},
								"down": {"uv": [16, 48], "uv_size": [-3, -2]}
							}
						},
						{
							"origin": [-3.05, 3, -3.05],
							"size": [6.1, 1, 6.1],
							"uv": {
								"north": {"uv": [13, 46], "uv_size": [3, 2]},
								"east": {"uv": [13, 46], "uv_size": [3, 2]},
								"south": {"uv": [13, 51], "uv_size": [3, 1]},
								"west": {"uv": [13, 51], "uv_size": [3, 1]},
								"up": {"uv": [16, 48], "uv_size": [-3, -2]},
								"down": {"uv": [16, 48], "uv_size": [-3, -2]}
							}
						},
						{
							"origin": [-3.05, 5, -3.05],
							"size": [6.1, 1, 6.1],
							"uv": {
								"north": {"uv": [13, 51], "uv_size": [3, 1]},
								"east": {"uv": [13, 46], "uv_size": [3, 2]},
								"south": {"uv": [13, 46], "uv_size": [3, 2]},
								"west": {"uv": [13, 48], "uv_size": [3, 1]},
								"up": {"uv": [16, 48], "uv_size": [-3, -2]},
								"down": {"uv": [16, 48], "uv_size": [-3, -2]}
							}
						},
						{
							"origin": [-3.05, 7, -3.05],
							"size": [6.1, 1, 6.1],
							"uv": {
								"north": {"uv": [13, 51], "uv_size": [3, 1]},
								"east": {"uv": [13, 48], "uv_size": [3, 1]},
								"south": {"uv": [13, 51], "uv_size": [3, 1]},
								"west": {"uv": [13, 46], "uv_size": [3, 2]},
								"up": {"uv": [16, 48], "uv_size": [-3, -2]},
								"down": {"uv": [16, 48], "uv_size": [-3, -2]}
							}
						},
						{
							"origin": [-3.05, 9, -3.05],
							"size": [6.1, 1.1, 6.1],
							"uv": {
								"north": {"uv": [13, 46], "uv_size": [3, 2]},
								"east": {"uv": [13, 46], "uv_size": [3, 2]},
								"south": {"uv": [13, 46], "uv_size": [3, 2]},
								"west": {"uv": [13, 48], "uv_size": [3, 1]},
								"up": {"uv": [16, 48], "uv_size": [-3, -2]},
								"down": {"uv": [16, 48], "uv_size": [-3, -2]}
							}
						},
						{
							"origin": [-3, 0, -3],
							"size": [6, 10, 6],
							"uv": {
								"north": {"uv": [59, 53], "uv_size": [5, 11]},
								"east": {"uv": [59, 53], "uv_size": [5, 11]},
								"south": {"uv": [59, 53], "uv_size": [5, 11]},
								"west": {"uv": [59, 53], "uv_size": [5, 11]},
								"up": {"uv": [64, 64], "uv_size": [-5, -11]},
								"down": {"uv": [64, 64], "uv_size": [-5, -11]}
							}
						}
					]
				}
			]
		}
	]
}